copyup/__init__.py
copyup-0.0.0.dist-info/LICENSE
copyup-0.0.0.dist-info/WHEEL
copyup-0.0.0.dist-info/METADATA
copyup-0.0.0.dist-info/RECORD
